AUTHORS.rst
CONTRIBUTING.rst
HISTORY.rst
LICENSE
MANIFEST.in
README.rst
setup.cfg
setup.py
docs/Makefile
docs/authors.rst
docs/conf.py
docs/contributing.rst
docs/history.rst
docs/index.rst
docs/installation.rst
docs/make.bat
docs/readme.rst
docs/usage.rst
holdmykeys/__init__.py
holdmykeys/cli.py
holdmykeys/holdmykeys.py
holdmykeys.egg-info/PKG-INFO
holdmykeys.egg-info/SOURCES.txt
holdmykeys.egg-info/dependency_links.txt
holdmykeys.egg-info/entry_points.txt
holdmykeys.egg-info/not-zip-safe
holdmykeys.egg-info/requires.txt
holdmykeys.egg-info/top_level.txt
tests/test_holdmykeys.py