Metadata-Version: 1.1
Name: holdmykeys
Version: 0.1.0
Summary: TODO
Home-page: https://github.com/hvnsweeting/holdmykeys
Author: Viet Hung Nguyen
Author-email: hvn@familug.org
License: MIT license
Keywords: holdmykeys
Platform: UNKNOWN
Classifier: Development Status :: 2 - Pre-Alpha
Classifier: Intended Audience :: Developers
Classifier: License :: OSI Approved :: MIT License
Classifier: Natural Language :: English
Classifier: Programming Language :: Python :: 2
Classifier: Programming Language :: Python :: 2.7
Classifier: Programming Language :: Python :: 3
Classifier: Programming Language :: Python :: 3.4
Classifier: Programming Language :: Python :: 3.5
Classifier: Programming Language :: Python :: 3.6
